TkEasyGo/__init__.py
TkEasyGo/builder.py
TkEasyGo/core.py
TkEasyGo/events.py
TkEasyGo/layout.py
TkEasyGo/platform.py
TkEasyGo/simple_variable.py
TkEasyGo/simple_window.py
TkEasyGo/themes.py
TkEasyGo/module/__init__.py
TkEasyGo/module/core.py
TkEasyGo/module/dialogs.py
TkEasyGo/module/utils.py
TkEasyGo/module/widgets.py
TkEasyGo-0.3.0.dist-info/LICENSE
TkEasyGo-0.3.0.dist-info/METADATA
TkEasyGo-0.3.0.dist-info/WHEEL
TkEasyGo-0.3.0.dist-info/entry_points.txt
TkEasyGo-0.3.0.dist-info/top_level.txt
TkEasyGo-0.3.0.dist-info/RECORD
