Metadata-Version: 2.1
Name: TkEasyGo
Version: 0.3.0
Summary: A simple cross-platform GUI generator.
Home-page: https://github.com/TkEasyGo/TkEasyGo
Author: TkEasyGo
Author-email: tkeasygo@gmail.com
Classifier: Development Status :: 3 - Alpha
Classifier: Intended Audience :: Developers
Classifier: License :: OSI Approved :: MIT License
Classifier: Programming Language :: Python :: 3
Classifier: Programming Language :: Python :: 3.7
Classifier: Programming Language :: Python :: 3.8
Classifier: Programming Language :: Python :: 3.9
Classifier: Programming Language :: Python :: 3.10
Classifier: Programming Language :: Python :: 3.11
Classifier: Programming Language :: Python :: 3.12
Classifier: Operating System :: OS Independent
Classifier: Environment :: Console
Requires-Python: >=3.7
License-File: LICENSE
Requires-Dist: ttkbootstrap (>=1.0.0)
Requires-Dist: Pillow (>=8.0.0)
